{
  "name": "Foods",
  "icon": "courageous:pear",
  "category": "food_category",
  "pages": [
    {
      "type": "spotlight",
      "anchor": "avocado",
      "item": "courageous:avocado",
      "text": "Food Points: 2$(br)Saturation: 0.1$()$(br)Obtained From: $(l:food/harvesting)Harvesting$() an $(l:exploration/trees#avocado_tree)avocado tree$()."
    },
    {
      "type": "spotlight",
      "anchor": "orange",
      "item": "courageous:orange",
      "text": "Food Points: 3$(br)Saturation: 0.3$()$(br)Obtained From: $(l:food/harvesting)Harvesting$() an $(l:exploration/trees#orange_tree)orange tree$()."
    },
    {
      "type": "spotlight",
      "anchor": "pear",
      "item": "courageous:pear",
      "text": "Food Points: 2$(br)Saturation: 0.1$()$(br)Obtained From: $(l:food/harvesting)Harvesting$() an $(l:exploration/trees#pear_tree)pear tree$()."
    },
    {
      "type": "spotlight",
      "anchor": "plum",
      "item": "courageous:plum",
      "text": "Food Points: 3$(br)Saturation: 0.3$()$(br)Obtained From: $(l:food/harvesting)Harvesting$() a $(l:exploration/trees#plum)plum tree$()."
    },
    {
      "type": "spotlight",
      "anchor": "lemon",
      "item": "courageous:lemon",
      "text": "Food Points: 1$(br)Saturation: 0.15$()$(br)Obtained From: $(l:food/harvesting)Harvesting$() a $(l:exploration/trees#lemon_tree)lemon tree$()."
    },
    {
      "type": "spotlight",
      "anchor": "kiwi_fruit",
      "item": "courageous:kiwi_fruit",
      "text": "Food Points: 3$(br)Saturation: 0.35$()$(br)Obtained From: $(l:food/harvesting)Harvesting$() a $(l:exploration/trees#kiwi_fruit_tree)kiwi fruit tree$()."
    }
  ]
}